subsetter/__init__.py
subsetter/__main__.py
subsetter/_version.py
subsetter/common.py
subsetter/config_model.py
subsetter/filters.py
subsetter/metadata.py
subsetter/plan_model.py
subsetter/planner.py
subsetter/sampler.py
subsetter/solver.py
subsetter-0.4.4.dist-info/licenses/LICENSE
subsetter-0.4.4.dist-info/METADATA
subsetter-0.4.4.dist-info/WHEEL
subsetter-0.4.4.dist-info/entry_points.txt
subsetter-0.4.4.dist-info/top_level.txt
subsetter-0.4.4.dist-info/RECORD
