Metadata-Version: 2.4
Name: subsetter
Version: 0.4.4
Summary: MySQL database subsetting CLI tool
Home-page: http://github.com/msg555/subsetter/
Author: Mark Gordon
Author-email: msg555@gmail.com
Classifier: Programming Language :: Python
Classifier: Programming Language :: Python :: 3
Classifier: Programming Language :: Python :: 3.8
Classifier: Programming Language :: Python :: 3.9
Classifier: Programming Language :: Python :: 3.10
Classifier: Programming Language :: Python :: 3.11
Classifier: Programming Language :: Python :: 3.12
Classifier: License :: OSI Approved :: BSD License
Classifier: Operating System :: OS Independent
Requires-Python: >=3.8
License-File: LICENSE
Requires-Dist: sqlalchemy[mypy]~=2.0
Requires-Dist: pydantic~=2.6
Requires-Dist: pyyaml~=6.0
Requires-Dist: faker~=19.3
Requires-Dist: typing-extensions
Provides-Extra: all
Requires-Dist: sqlalchemy[postgresql_psycopg2binary,pymysql]; extra == "all"
Provides-Extra: pymysql
Requires-Dist: sqlalchemy[pymysql]; extra == "pymysql"
Provides-Extra: postgresql
Requires-Dist: sqlalchemy[postgresql]; extra == "postgresql"
Provides-Extra: postgresql-psycopg2binary
Requires-Dist: sqlalchemy[postgresql_psycopg2binary]; extra == "postgresql-psycopg2binary"
Dynamic: license-file
